{
  "$schema": "../../schemas/v2/spells.schema.json",
  "entity_id": "fire_rain",
  "name": "Fire Rain",
  "category": "Spell",
  "magic_school": "Elemental",
  "rank": "IV",
  "description": "Fire projectiles that deal continuous damage over a wide area.",
  "image_required": true,
  "tags": [],
  "mechanics": {
    "damage_modifiers": [
      {
        "multiplier": 1.2,
        "target_types": [
          "Creature"
        ]
      },
      {
        "multiplier": 0.5,
        "target_types": [
          "Building"
        ]
      }
    ],
    "infusion": {
      "id": "fire_infusion"
    }
  },
  "damage": 600,
  "damage_overrides": {
    "Building": 0,
    "Lifestone": 0,
    "Creature": 0,
    "Spellcaster": 0
  },
  "range": 45,
  "duration": 15,
  "charges": 1,
  "recharge_time": 120,
  "cast_time": 0,
  "knowledge_cost": 500
}
